{
  "description": "NodeDaemonEndpoints lists ports opened by daemons running on the Node.",
  "type": "object",
  "properties": {
    "kubeletEndpoint": {
      "description": "DaemonEndpoint contains information about a single Daemon endpoint.",
      "type": [
        "object",
        "null"
      ],
      "required": [
        "Port"
      ],
      "properties": {
        "Port": {
          "description": "Port number of the given endpoint.",
          "type": "integer",
          "format": "int32"
        }
      }
    }
  },
  "$schema": "http://json-schema.org/schema#"
}